Launchpyx/__init__.py
Launchpyx/launchpad_control.py
Launchpyx/utils.py
Launchpyx-0.1.0.dist-info/LICENSE
Launchpyx-0.1.0.dist-info/METADATA
Launchpyx-0.1.0.dist-info/WHEEL
Launchpyx-0.1.0.dist-info/top_level.txt
Launchpyx-0.1.0.dist-info/RECORD
